{
  "id": "10184",
  "key": "GG-181",
  "fields": {
    "summary": "Task: Conduct User Acceptance Testing for Custom Fields",
    "description": {
      "type": "doc",
      "version": 1,
      "content": [
        {
          "type": "heading",
          "attrs": {
            "level": 2
          },
          "content": [
            {
              "type": "text",
              "text": "Use case:"
            }
          ]
        },
        {
          "type": "paragraph",
          "content": [
            {
              "type": "text",
              "text": "As a "
            },
            {
              "type": "text",
              "text": "Quality Assurance Tester",
              "marks": [
                {
                  "type": "strong"
                }
              ]
            },
            {
              "type": "text",
              "text": ", "
            },
            {
              "type": "hardBreak"
            },
            {
              "type": "text",
              "text": "I want to conduct User Acceptance Testing for Custom Fields, "
            },
            {
              "type": "hardBreak"
            },
            {
              "type": "text",
              "text": "so that I can ensure the custom fields functionality meets the specified requirements and is user-friendly. "
            }
          ]
        },
        {
          "type": "rule"
        },
        {
          "type": "heading",
          "attrs": {
            "level": 2
          },
          "content": [
            {
              "type": "text",
              "text": "Acceptance criteria:"
            }
          ]
        },
        {
          "type": "paragraph",
          "content": [
            {
              "type": "text",
              "text": "GIVEN",
              "marks": [
                {
                  "type": "em"
                }
              ]
            },
            {
              "type": "text",
              "text": " the custom fields functionality is developed and integrated with the application, "
            },
            {
              "type": "hardBreak"
            },
            {
              "type": "text",
              "text": "WHEN",
              "marks": [
                {
                  "type": "em"
                }
              ]
            },
            {
              "type": "text",
              "text": " I access the application interface to interact with custom fields, "
            },
            {
              "type": "hardBreak"
            },
            {
              "type": "text",
              "text": "AND",
              "marks": [
                {
                  "type": "em"
                }
              ]
            },
            {
              "type": "text",
              "text": " I input and retrieve data using the custom fields, "
            },
            {
              "type": "hardBreak"
            },
            {
              "type": "text",
              "text": "THEN",
              "marks": [
                {
                  "type": "em"
                }
              ]
            },
            {
              "type": "text",
              "text": " I should be able to validate that the custom fields work as expected and are displayed accurately in the UI. "
            }
          ]
        },
        {
          "type": "rule"
        },
        {
          "type": "heading",
          "attrs": {
            "level": 2
          },
          "content": [
            {
              "type": "text",
              "text": "Technical notes:"
            }
          ]
        },
        {
          "type": "paragraph",
          "content": [
            {
              "type": "text",
              "text": "It's essential to focus on both positive and negative test scenarios for the custom fields, including boundary values and error handling. Additionally, ensure that the testing environment closely resembles the production environment to accurately assess user experience."
            }
          ]
        }
      ]
    },
    "issuetype": {
      "id": "10011",
      "name": "Story"
    },
    "status": {
      "name": "Defined"
    },
    "priority": {
      "name": "Medium"
    },
    "creator": {
      "displayName": "Stan Dalence",
      "emailAddress": ""
    },
    "reporter": {
      "displayName": "Stan Dalence",
      "emailAddress": ""
    },
    "assignee": null,
    "created": "2025-02-09T16:13:11.464-0400",
    "updated": "2025-02-18T10:24:42.793-0400",
    "duedate": null,
    "labels": [],
    "components": [],
    "fixVersions": [],
    "attachment": [],
    "subtasks": [],
    "issuelinks": [],
    "comments": [],
    "customfield_10030": {
      "name": "Submitted forms",
      "value": null
    },
    "customfield_10031": {
      "name": "Total forms",
      "value": null
    },
    "customfield_10032": {
      "name": "Design",
      "value": null
    },
    "customfield_10034": {
      "name": "Project overview key",
      "value": null
    },
    "customfield_10035": {
      "name": "Project overview status",
      "value": null
    },
    "customfield_10027": {
      "name": "[CHART] Time in Status",
      "value": null
    },
    "customfield_10028": {
      "name": "Locked forms",
      "value": null
    },
    "customfield_10029": {
      "name": "Open forms",
      "value": null
    },
    "customfield_10020": {
      "name": "Sprint",
      "value": null
    },
    "customfield_10021": {
      "name": "Flagged",
      "value": null
    },
    "customfield_10022": {
      "name": "Target start",
      "value": null
    },
    "customfield_10023": {
      "name": "Target end",
      "value": null
    },
    "customfield_10024": {
      "name": "Sentiment",
      "value": null
    },
    "customfield_10025": {
      "name": "Goals",
      "value": null
    },
    "customfield_10026": {
      "name": "[CHART] Date of First Response",
      "value": null
    },
    "customfield_10016": {
      "name": "Story point estimate",
      "value": null
    },
    "customfield_10017": {
      "name": "Issue color",
      "value": null
    },
    "customfield_10018": {
      "name": "Parent Link",
      "value": {
        "hasEpicLinkFieldDependency": false,
        "showField": false,
        "nonEditableReason": {
          "reason": "EPIC_LINK_SHOULD_BE_USED",
          "message": "To set an epic as the parent, use the epic link instead"
        }
      }
    },
    "customfield_10019": {
      "name": "Rank",
      "value": "0|i0014v:"
    },
    "customfield_10010": {
      "name": "Request Type",
      "value": null
    },
    "customfield_10014": {
      "name": "Epic Link",
      "value": "GG-119"
    },
    "customfield_10015": {
      "name": "Start date",
      "value": null
    },
    "customfield_10005": {
      "name": "Change type",
      "value": null
    },
    "customfield_10006": {
      "name": "Change risk",
      "value": null
    },
    "customfield_10007": {
      "name": "Change reason",
      "value": null
    },
    "customfield_10008": {
      "name": "Actual start",
      "value": null
    },
    "customfield_10009": {
      "name": "Actual end",
      "value": null
    },
    "customfield_10000": {
      "name": "development",
      "value": "{}"
    },
    "customfield_10001": {
      "name": "Team",
      "value": null
    },
    "customfield_10002": {
      "name": "Organizations",
      "value": []
    },
    "customfield_10003": {
      "name": "Approvers",
      "value": null
    },
    "customfield_10004": {
      "name": "Impact",
      "value": null
    },
    "customfield_10039": {
      "name": "Story Points",
      "value": null
    }
  }
}